{
    "$schema": "http://json-schema.org/draft-04/schema#",
    "$ref": "#/definitions/QueryConnectionConsensusStateRequest",
    "definitions": {
        "QueryConnectionConsensusStateRequest": {
            "properties": {
                "connection_id": {
                    "type": "string",
                    "description": "connection identifier"
                },
                "revision_number": {
                    "type": "string"
                },
                "revision_height": {
                    "type": "string"
                }
            },
            "additionalProperties": true,
            "type": "object",
            "title": "Query Connection Consensus State Request",
            "description": "QueryConnectionConsensusStateRequest is the request type for the Query/ConnectionConsensusState RPC method"
        }
    }
}